ivpm/__init__.py
ivpm/__main__.py
ivpm/arg_utils.py
ivpm/cache.py
ivpm/env_spec.py
ivpm/ivpm_subprocess.py
ivpm/ivpm_yaml_reader.py
ivpm/ivpm_yaml_writer.py
ivpm/msg.py
ivpm/out_wrapper.py
ivpm/package.py
ivpm/package_updater.py
ivpm/packages_info.py
ivpm/proj_info.py
ivpm/project_ops.py
ivpm/project_ops_info.py
ivpm/project_sync.py
ivpm/subprocess_runner.py
ivpm/update_event.py
ivpm/update_listener.py
ivpm/update_tui.py
ivpm/utils.py
ivpm/cmds/__init__.py
ivpm/cmds/cmd_activate.py
ivpm/cmds/cmd_build.py
ivpm/cmds/cmd_cache.py
ivpm/cmds/cmd_clone.py
ivpm/cmds/cmd_git_status.py
ivpm/cmds/cmd_git_update.py
ivpm/cmds/cmd_init.py
ivpm/cmds/cmd_pkg_info.py
ivpm/cmds/cmd_share.py
ivpm/cmds/cmd_snapshot.py
ivpm/cmds/cmd_status.py
ivpm/cmds/cmd_sync.py
ivpm/cmds/cmd_update.py
ivpm/handlers/__init__.py
ivpm/handlers/package_handler.py
ivpm/handlers/package_handler_list.py
ivpm/handlers/package_handler_python.py
ivpm/handlers/package_handler_rgy.py
ivpm/pkg_info/pkg_compile_flags.py
ivpm/pkg_info/pkg_info.py
ivpm/pkg_info/pkg_info_loader.py
ivpm/pkg_info/pkg_info_rgy.py
ivpm/pkg_types/__init__.py
ivpm/pkg_types/package_dir.py
ivpm/pkg_types/package_file.py
ivpm/pkg_types/package_gh_rls.py
ivpm/pkg_types/package_git.py
ivpm/pkg_types/package_http.py
ivpm/pkg_types/package_pypi.py
ivpm/pkg_types/package_url.py
ivpm/pkg_types/pkg_type_rgy.py
ivpm/pywrap/__init__.py
ivpm/pywrap/__main__.py
ivpm/schema/ivpm.json
ivpm/setup/__init__.py
ivpm/setup/build_ext.py
ivpm/setup/install_lib.py
ivpm/setup/ivpm_data.py
ivpm/setup/wrapper.py
ivpm/share/ivpm.json
ivpm/share/skill.md
ivpm/share/cmake/ivpm.cmake
ivpm/templates/init.py
ivpm/templates/ivpm.info
ivpm/templates/ivpm.py
ivpm/templates/ivpm.yaml
ivpm/templates/packages.mf
ivpm-2.5.0.21549860151.dist-info/licenses/LICENSE
ivpm-2.5.0.21549860151.dist-info/METADATA
ivpm-2.5.0.21549860151.dist-info/WHEEL
ivpm-2.5.0.21549860151.dist-info/entry_points.txt
ivpm-2.5.0.21549860151.dist-info/top_level.txt
ivpm-2.5.0.21549860151.dist-info/RECORD
