Metadata-Version: 2.4
Name: ivpm
Version: 2.5.0.21549860151
Summary: IVPM (IP and Verification Package Manager) is a project-internal package manager.
Author-email: Matthew Ballance <matt.ballance@gmail.com>
License: BSD 3-Clause License
License-File: LICENSE
Requires-Dist: httpx<1.0,>=0.28.1
Requires-Dist: pyyaml
Requires-Dist: pyyaml-srcinfo-loader
Requires-Dist: rich
Requires-Dist: setuptools
Requires-Dist: toposort
Dynamic: license-file
